[
    {
        "id": 0,
        "themeType": "CardBack",
        "themeId": 2001,
        "resourcePath": "cardback_0"
    },
    {
        "id": 1,
        "themeType": "CardBack",
        "themeId": 2002,
        "resourcePath": "cardback_1"
    },
    {
        "id": 2,
        "themeType": "CardBack",
        "themeId": 2003,
        "resourcePath": "cardback_2"
    },
    {
        "id": 3,
        "themeType": "CardBack",
        "themeId": 2004,
        "resourcePath": "cardback_3"
    },
    {
        "id": 4,
        "themeType": "CardBack",
        "themeId": 2005,
        "resourcePath": "cardback_4"
    },
    {
        "id": 5,
        "themeType": "CardBack",
        "themeId": 2006,
        "resourcePath": "cardback_5"
    },
    {
        "id": 6,
        "themeType": "CardBack",
        "themeId": 2007,
        "resourcePath": "cardback_6"
    },
    {
        "id": 7,
        "themeType": "CardBack",
        "themeId": 2008,
        "resourcePath": "cardback_7"
    },
    {
        "id": 8,
        "themeType": "CardBack",
        "themeId": 2009,
        "resourcePath": "cardback_8"
    },
    {
        "id": 9,
        "themeType": "CardBack",
        "themeId": 2010,
        "resourcePath": "cardback_9"
    },
    {
        "id": 10,
        "themeType": "CardBack",
        "themeId": 2011,
        "resourcePath": "cardback_10"
    },
    {
        "id": 11,
        "themeType": "CardBack",
        "themeId": 2012,
        "resourcePath": "cardback_11"
    },
    {
        "id": 12,
        "themeType": "CardBack",
        "themeId": 2013,
        "resourcePath": "cardback_12"
    },
    {
        "id": 13,
        "themeType": "CardBack",
        "themeId": 2014,
        "resourcePath": "cardback_13"
    },
    {
        "id": 14,
        "themeType": "CardBack",
        "themeId": 2015,
        "resourcePath": "cardback_14"
    },
    {
        "id": 15,
        "themeType": "CardBack",
        "themeId": 2016,
        "resourcePath": "cardback_15"
    },
    {
        "id": 16,
        "themeType": "CardBack",
        "themeId": 2017,
        "resourcePath": "cardback_16"
    }
]